kendrick/__init__.py
kendrick/_modidx.py
kendrick/core.py
kendrick/explore.py
kendrick-0.0.3.dist-info/LICENSE
kendrick-0.0.3.dist-info/METADATA
kendrick-0.0.3.dist-info/WHEEL
kendrick-0.0.3.dist-info/entry_points.txt
kendrick-0.0.3.dist-info/top_level.txt
kendrick-0.0.3.dist-info/RECORD
