Metadata-Version: 2.1
Name: kendrick
Version: 0.0.3
Summary: Towards automating Kendrick mass plots
Home-page: https://github.com/fligt/kendrick
Author: Frank Ligterink
Author-email: frank.ligterink@gmail.com
License: MIT License
Keywords: hrms nbdev jupyter notebook python
Classifier: Development Status :: 4 - Beta
Classifier: Intended Audience :: Developers
Classifier: Natural Language :: English
Classifier: Programming Language :: Python :: 3.8
Classifier: Programming Language :: Python :: 3.9
Classifier: Programming Language :: Python :: 3.10
Classifier: License :: OSI Approved :: MIT License
Requires-Python: >=3.8
License-File: LICENSE
Requires-Dist: pyopenms
Requires-Dist: datashader
Requires-Dist: dask
Requires-Dist: dask-expr
Requires-Dist: scipy
Requires-Dist: pandas
Requires-Dist: jupyter
Requires-Dist: molmass
Requires-Dist: mendeleev
Requires-Dist: numpy
Requires-Dist: matplotlib
Requires-Dist: ipyleaflet
Requires-Dist: plotly
Requires-Dist: pyRawTools
Requires-Dist: polars
Provides-Extra: dev
